firstlvbo/__init__.py
firstlvbo/__version__.py
firstlvbo/core.py
firstlvbo-0.0.2.dist-info/LICENSE
firstlvbo-0.0.2.dist-info/METADATA
firstlvbo-0.0.2.dist-info/WHEEL
firstlvbo-0.0.2.dist-info/top_level.txt
firstlvbo-0.0.2.dist-info/RECORD
